database.py
kitaab.py
pygithub.py
terminal.py
kitaab-0.0.5.dist-info/LICENSE
kitaab-0.0.5.dist-info/METADATA
kitaab-0.0.5.dist-info/WHEEL
kitaab-0.0.5.dist-info/top_level.txt
kitaab-0.0.5.dist-info/RECORD
