Metadata-Version: 2.1
Name: kitaab
Version: 0.0.5
Summary: kitaab is a cli note-taking app
Author: Shaik Fareed Ahammad
Author-email: fareedahmad1097@gmail.com
Classifier: Programming Language :: Python :: 3
Classifier: License :: OSI Approved :: MIT License
Classifier: Operating System :: OS Independent
Requires-Python: >=3.10
License-File: LICENSE
Requires-Dist: rich (>=12.4.4)
Requires-Dist: PyGithub (>=1.55)
